MANIFEST.in
README.rst
requirements.txt
setup.cfg
setup.py
djmicrosip_reorden/__init__.py
djmicrosip_reorden/__init__.pyc
djmicrosip_reorden/config.pyc
djmicrosip_reorden/forms.pyc
djmicrosip_reorden/models.pyc
djmicrosip_reorden/urls.pyc
djmicrosip_reorden/views.pyc
djmicrosip_reorden.egg-info/PKG-INFO
djmicrosip_reorden.egg-info/SOURCES.txt
djmicrosip_reorden.egg-info/dependency_links.txt
djmicrosip_reorden.egg-info/requires.txt
djmicrosip_reorden.egg-info/top_level.txt
djmicrosip_reorden/custom_db/__init__.py
djmicrosip_reorden/custom_db/__init__.pyc
djmicrosip_reorden/custom_db/sql_queries.pyc
djmicrosip_reorden/static/djmicrosip_reorden/js/genera_orden.js
djmicrosip_reorden/static/djmicrosip_reorden/js/tarea_preferencias.js
djmicrosip_reorden/templates/djmicrosip_reorden/base.html
djmicrosip_reorden/templates/djmicrosip_reorden/entradas_automaticas.html
djmicrosip_reorden/templates/djmicrosip_reorden/generar.html
djmicrosip_reorden/templates/djmicrosip_reorden/index.html
djmicrosip_reorden/templates/djmicrosip_reorden/pedidos.html
djmicrosip_reorden/templates/djmicrosip_reorden/preferencias.html
djmicrosip_reorden/templates/djmicrosip_reorden/salidas_automaticas.html